{
  "appPageId" : "7fe97e67-1ab0-4fe3-8497-ddfeb8bcee4b",
  "componentName" : "siteforce:sldsOneColLayout",
  "dataProviders" : [ ],
  "id" : "f11cecdf-1992-4639-99da-a962a2f37d2a",
  "label" : "Topic Catalog",
  "regions" : [ {
    "components" : [ {
      "componentAttributes" : {
        "bannerText" : "",
        "bannerTextWithKnowledge" : "Explore other <a href=\"javascript:void(0)\" class=\"headlineArticles\">articles</a> and <a href=\"javascript:void(0)\" class=\"headlineDiscussions\">discussions</a> on this topic.",
        "bannerTextWithoutKnowledge" : "Explore other <a href=\"javascript:void(0)\" class=\"headlineDiscussions\">discussions</a> on this topic.",
        "pageType" : "",
        "showSubTopics" : true,
        "title" : "Topics",
        "uniqueNameOrId" : ""
      },
      "componentName" : "forceCommunity:headline",
      "id" : "3f36aba8-591c-4617-a910-335e467a6d14",
      "renderPriority" : "NEUTRAL",
      "renditionMap" : { },
      "type" : "component"
    } ],
    "id" : "a4fff7a7-dcfc-4c42-b71f-bc2974785a79",
    "regionName" : "header",
    "type" : "region"
  }, {
    "components" : [ {
      "componentAttributes" : { },
      "componentName" : "forceCommunity:topicCatalog",
      "id" : "3db4e02b-fa04-4c47-a2f1-516888ad0e02",
      "renderPriority" : "NEUTRAL",
      "renditionMap" : { },
      "type" : "component"
    } ],
    "id" : "9a78e7e4-c45a-44f8-b13f-3fc84d921381",
    "regionName" : "content",
    "type" : "region"
  }, {
    "id" : "4b81820c-2906-411d-b6f2-ef08f26eea26",
    "regionName" : "footer",
    "type" : "region"
  }, {
    "components" : [ {
      "componentAttributes" : {
        "customHeadTags" : "",
        "description" : "",
        "title" : "Topic Catalog"
      },
      "componentName" : "forceCommunity:seoAssistant",
      "id" : "c7fd3415-6300-4965-9403-93aefa13ef6f",
      "renditionMap" : { },
      "type" : "component"
    } ],
    "id" : "32343778-27db-494f-8bac-fb98900e4ad6",
    "regionName" : "sfdcHiddenRegion",
    "type" : "region"
  } ],
  "themeLayoutType" : "Inner",
  "type" : "view",
  "viewType" : "topic-catalog"
}